{
  "project_info": {
    "project_number": "43779756558",
    "firebase_url": "https://marrymax-150206.firebaseio.com",
    "project_id": "marrymax-150206",
    "storage_bucket": "marrymax-150206.appspot.com"
  },
  "client": [
    {
      "client_info": {
        "mobilesdk_app_id": "1:43779756558:android:9d7afe6d6767b0f8",
        "android_client_info": {
          "package_name": "com.chicsol.alfalah"
        }
      },
      "oauth_client": [
        {
          "client_id": "43779756558-ogok7k9unidoj81n98n58kshtt53g00h.apps.googleusercontent.com",
          "client_type": 1,
          "android_info": {
            "package_name": "com.chicsol.alfalah",
            "certificate_hash": "3cc582c83389c69451c2cee7588e7f38ad0a19fb"
          }
        },
        {
          "client_id": "43779756558-m1gc383p37tct4d1sejkbcojsc438bnb.apps.googleusercontent.com",
          "client_type": 3
        }
      ],
      "api_key": [
        {
          "current_key": "AIzaSyC5392yUwUCuuH3uEl95z4DrPSxkzEo1gA"
        }
      ],
      "services": {
        "analytics_service": {
          "status": 1
        },
        "appinvite_service": {
          "status": 2,
          "other_platform_oauth_client": [
            {
              "client_id": "43779756558-m1gc383p37tct4d1sejkbcojsc438bnb.apps.googleusercontent.com",
              "client_type": 3
            }
          ]
        },
        "ads_service": {
          "status": 2
        }
      }
    }
  ],
  "configuration_version": "1"
}